service_grpc/__init__.py
service_grpc/utils.py
service_grpc/bin/calculator_server
service_grpc/calculator_client/__init__.py
service_grpc/calculator_client/client.py
service_grpc/proto/__init__.py
service_grpc/proto/calculator.proto
service_grpc/proto/calculator_pb2.py
service_grpc/proto/calculator_pb2.pyi
service_grpc/proto/calculator_pb2_grpc.py
service_grpc/sdk/__init__.py
service_grpc/sdk/finish.py
service_grpc/sdk/init.py
service_grpc/sdk/run.py
service_grpc-0.0.5.dist-info/METADATA
service_grpc-0.0.5.dist-info/WHEEL
service_grpc-0.0.5.dist-info/RECORD
