Metadata-Version: 2.3
Name: service-grpc
Version: 0.0.5
Summary: This is a test of grpc service.
License: MIT
Requires-Python: >=3.8
Requires-Dist: grpcio-tools==1.68.0
Requires-Dist: grpcio==1.68.0
Requires-Dist: protobuf==5.28.3
